{
"autoplayBgm":true,"autoplayBgs":false,"battleback1Name":"","battleback2Name":"","bgm":{"name":"Ship1","pan":0,"pitch":100,"volume":90},"bgs":{"name":"","pan":0,"pitch":100,"volume":90},"disableDashing":false,"displayName":"","encounterList":[],"encounterStep":30,"height":5,"note":"","parallaxLoopX":false,"parallaxLoopY":false,"parallaxName":"","parallaxShow":true,"parallaxSx":0,"parallaxSy":0,"scrollType":0,"specifyBattleback":false,"tilesetId":1,"width":5,
"data":[0,0,0,0,0,0,0,0,0,0,0,0,0,0,0,0,0,0,0,0,0,0,0,0,0,0,0,0,0,0,0,0,0,0,0,0,0,0,0,0,0,0,0,0,0,0,0,0,0,0,0,0,0,0,0,0,0,0,0,0,0,0,0,0,0,0,0,0,0,0,0,0,0,0,0,0,0,0,0,0,0,0,0,0,0,0,0,0,0,0,0,0,0,0,0,0,0,0,0,0,0,0,0,0,0,0,0,0,0,0,0,0,0,0,0,0,0,0,0,0,0,0,0,0,0,0,0,0,0,0,0,0,0,0,0,0,0,0,0,0,0,0,0,0,0,0,0,0,0,0],
"events":[
null,
{"id":1,"name":"EV001","note":"","pages":[{"conditions":{"actorId":1,"actorValid":false,"itemId":1,"itemValid":false,"selfSwitchCh":"A","selfSwitchValid":false,"switch1Id":1,"switch1Valid":false,"switch2Id":1,"switch2Valid":false,"variableId":1,"variableValid":false,"variableValue":0},"directionFix":false,"image":{"characterIndex":0,"characterName":"","direction":2,"pattern":0,"tileId":0},"list":[{"code":111,"indent":0,"parameters":[4,1,0]},{"code":235,"indent":1,"parameters":[1]},{"code":235,"indent":1,"parameters":[2]},{"code":235,"indent":1,"parameters":[3]},{"code":124,"indent":1,"parameters":[1]},{"code":0,"indent":1,"parameters":[]},{"code":412,"indent":0,"parameters":[]},{"code":231,"indent":0,"parameters":[1,"7-17",0,0,0,0,100,100,255,0]},{"code":101,"indent":0,"parameters":["",0,0,2]},{"code":401,"indent":0,"parameters":["【？？】"]},{"code":401,"indent":0,"parameters":["对于你这种小虫子，"]},{"code":401,"indent":0,"parameters":["我是不可能留情的！"]},{"code":101,"indent":0,"parameters":["player",7,0,2]},{"code":401,"indent":0,"parameters":["【辰远】"]},{"code":401,"indent":0,"parameters":["啊！！！"]},{"code":250,"indent":0,"parameters":[{"name":"[taji","volume":90,"pitch":100,"pan":0}]},{"code":230,"indent":0,"parameters":[60]},{"code":250,"indent":0,"parameters":[{"name":"[Bite","volume":90,"pitch":100,"pan":0}]},{"code":222,"indent":0,"parameters":[]},{"code":230,"indent":0,"parameters":[180]},{"code":232,"indent":0,"parameters":[1,0,0,0,0,-558,100,100,255,0,240,true]},{"code":101,"indent":0,"parameters":["",0,2,2]},{"code":401,"indent":0,"parameters":["就这样……"]},{"code":101,"indent":0,"parameters":["",0,2,2]},{"code":401,"indent":0,"parameters":["辰远在死亡的边缘疯狂试探……\\!"]},{"code":401,"indent":0,"parameters":["即使在刚开始还能够躲开这一次次踩踏……\\!"]},{"code":401,"indent":0,"parameters":["但是随着体力的渐渐不支……\\!"]},{"code":401,"indent":0,"parameters":["再也没有力气拖动自己的身体前行……"]},{"code":101,"indent":0,"parameters":["",0,2,2]},{"code":401,"indent":0,"parameters":["那就只能静静的看着那巨大的脚跟……\\!"]},{"code":401,"indent":0,"parameters":["从自己的头上压下来了……\\!\\!"]},{"code":401,"indent":0,"parameters":["于是辰远就被这样……磨成了鞋跟底下的渣子……\\!"]},{"code":401,"indent":0,"parameters":["为自己的生命划上了句号……"]},{"code":230,"indent":0,"parameters":[60]},{"code":101,"indent":0,"parameters":["player2(2)",1,0,2]},{"code":401,"indent":0,"parameters":["【娜】"]},{"code":401,"indent":0,"parameters":["唉……无法了……"]},{"code":230,"indent":0,"parameters":[240]},{"code":353,"indent":0,"parameters":[]},{"code":0,"indent":0,"parameters":[]}],"moveFrequency":3,"moveRoute":{"list":[{"code":0,"parameters":[]}],"repeat":true,"skippable":false,"wait":false},"moveSpeed":3,"moveType":0,"priorityType":0,"stepAnime":false,"through":false,"trigger":4,"walkAnime":true},{"conditions":{"actorId":1,"actorValid":false,"itemId":1,"itemValid":false,"selfSwitchCh":"A","selfSwitchValid":false,"switch1Id":1,"switch1Valid":false,"switch2Id":1,"switch2Valid":false,"variableId":44,"variableValid":true,"variableValue":20},"directionFix":false,"image":{"characterIndex":0,"characterName":"","direction":2,"pattern":0,"tileId":0},"list":[{"code":111,"indent":0,"parameters":[4,1,0]},{"code":235,"indent":1,"parameters":[1]},{"code":235,"indent":1,"parameters":[2]},{"code":235,"indent":1,"parameters":[3]},{"code":124,"indent":1,"parameters":[1]},{"code":0,"indent":1,"parameters":[]},{"code":412,"indent":0,"parameters":[]},{"code":231,"indent":0,"parameters":[1,"7-19",0,0,0,0,100,100,255,0]},{"code":101,"indent":0,"parameters":["player",3,0,2]},{"code":401,"indent":0,"parameters":["【辰远】"]},{"code":401,"indent":0,"parameters":["啊……不要在这……结束啊……"]},{"code":250,"indent":0,"parameters":[{"name":"[taji","volume":90,"pitch":100,"pan":0}]},{"code":230,"indent":0,"parameters":[60]},{"code":250,"indent":0,"parameters":[{"name":"[Bite","volume":90,"pitch":100,"pan":0}]},{"code":222,"indent":0,"parameters":[]},{"code":230,"indent":0,"parameters":[180]},{"code":101,"indent":0,"parameters":["Ay",0,0,2]},{"code":401,"indent":0,"parameters":["【安雅】"]},{"code":401,"indent":0,"parameters":["啊哈哈哈……"]},{"code":401,"indent":0,"parameters":["一不小心……就弄出麻烦了呢……"]},{"code":101,"indent":0,"parameters":["Ay",0,0,2]},{"code":401,"indent":0,"parameters":["【安雅】"]},{"code":401,"indent":0,"parameters":["算啦算啦……"]},{"code":401,"indent":0,"parameters":["反正没人知道呢，"]},{"code":401,"indent":0,"parameters":["赶紧清理掉……"]},{"code":101,"indent":0,"parameters":["",0,0,2]},{"code":401,"indent":0,"parameters":["就这样……\\!辰远在与安雅互动的过程中……"]},{"code":401,"indent":0,"parameters":["一不小心玩脱了……\\!"]},{"code":401,"indent":0,"parameters":["就落下了这个结果……\\!"]},{"code":401,"indent":0,"parameters":["很无奈的为自己的生命画上了句号……"]},{"code":230,"indent":0,"parameters":[240]},{"code":353,"indent":0,"parameters":[]},{"code":0,"indent":0,"parameters":[]}],"moveFrequency":3,"moveRoute":{"list":[{"code":0,"parameters":[]}],"repeat":true,"skippable":false,"wait":false},"moveSpeed":3,"moveType":0,"priorityType":0,"stepAnime":false,"through":false,"trigger":4,"walkAnime":true},{"conditions":{"actorId":1,"actorValid":false,"itemId":1,"itemValid":false,"selfSwitchCh":"A","selfSwitchValid":false,"switch1Id":1,"switch1Valid":false,"switch2Id":1,"switch2Valid":false,"variableId":44,"variableValid":true,"variableValue":50},"directionFix":false,"image":{"characterIndex":0,"characterName":"","direction":2,"pattern":0,"tileId":0},"list":[{"code":111,"indent":0,"parameters":[4,1,0]},{"code":235,"indent":1,"parameters":[1]},{"code":235,"indent":1,"parameters":[2]},{"code":235,"indent":1,"parameters":[3]},{"code":124,"indent":1,"parameters":[1]},{"code":0,"indent":1,"parameters":[]},{"code":412,"indent":0,"parameters":[]},{"code":231,"indent":0,"parameters":[1,"7-19",0,0,0,0,100,100,255,0]},{"code":101,"indent":0,"parameters":["player",3,0,2]},{"code":401,"indent":0,"parameters":["【辰远】"]},{"code":401,"indent":0,"parameters":["啊……不要在这……结束啊……"]},{"code":250,"indent":0,"parameters":[{"name":"[taji","volume":90,"pitch":100,"pan":0}]},{"code":230,"indent":0,"parameters":[60]},{"code":250,"indent":0,"parameters":[{"name":"[Bite","volume":90,"pitch":100,"pan":0}]},{"code":222,"indent":0,"parameters":[]},{"code":230,"indent":0,"parameters":[180]},{"code":101,"indent":0,"parameters":["Ay",0,0,2]},{"code":401,"indent":0,"parameters":["【安雅】"]},{"code":401,"indent":0,"parameters":["糟糕……"]},{"code":401,"indent":0,"parameters":["这一不小心……"]},{"code":401,"indent":0,"parameters":["刚才好像下脚太重了……"]},{"code":101,"indent":0,"parameters":["Ay",0,0,2]},{"code":401,"indent":0,"parameters":["【安雅】"]},{"code":401,"indent":0,"parameters":["哎呀哎呀……\\!"]},{"code":401,"indent":0,"parameters":["好可惜啊……\\!"]},{"code":401,"indent":0,"parameters":["我怎么会这样啊……"]},{"code":101,"indent":0,"parameters":["",0,0,2]},{"code":401,"indent":0,"parameters":["就这样……\\!辰远在与安雅互动的过程中……"]},{"code":401,"indent":0,"parameters":["一不小心玩脱了……\\!"]},{"code":401,"indent":0,"parameters":["就落下了这个结果……\\!"]},{"code":401,"indent":0,"parameters":["很无奈的为自己的生命画上了句号……"]},{"code":230,"indent":0,"parameters":[240]},{"code":353,"indent":0,"parameters":[]},{"code":0,"indent":0,"parameters":[]}],"moveFrequency":3,"moveRoute":{"list":[{"code":0,"parameters":[]}],"repeat":true,"skippable":false,"wait":false},"moveSpeed":3,"moveType":0,"priorityType":0,"stepAnime":false,"through":false,"trigger":4,"walkAnime":true},{"conditions":{"actorId":1,"actorValid":false,"itemId":1,"itemValid":false,"selfSwitchCh":"A","selfSwitchValid":false,"switch1Id":1,"switch1Valid":false,"switch2Id":1,"switch2Valid":false,"variableId":44,"variableValid":true,"variableValue":70},"directionFix":false,"image":{"characterIndex":0,"characterName":"","direction":2,"pattern":0,"tileId":0},"list":[{"code":111,"indent":0,"parameters":[4,1,0]},{"code":235,"indent":1,"parameters":[1]},{"code":235,"indent":1,"parameters":[2]},{"code":235,"indent":1,"parameters":[3]},{"code":124,"indent":1,"parameters":[1]},{"code":0,"indent":1,"parameters":[]},{"code":412,"indent":0,"parameters":[]},{"code":231,"indent":0,"parameters":[1,"7-19",0,0,0,0,100,100,255,0]},{"code":101,"indent":0,"parameters":["player",3,0,2]},{"code":401,"indent":0,"parameters":["【辰远】"]},{"code":401,"indent":0,"parameters":["啊……不要在这……结束啊……"]},{"code":250,"indent":0,"parameters":[{"name":"[taji","volume":90,"pitch":100,"pan":0}]},{"code":230,"indent":0,"parameters":[60]},{"code":250,"indent":0,"parameters":[{"name":"[Bite","volume":90,"pitch":100,"pan":0}]},{"code":222,"indent":0,"parameters":[]},{"code":230,"indent":0,"parameters":[180]},{"code":101,"indent":0,"parameters":["Ay",0,0,2]},{"code":401,"indent":0,"parameters":["【安雅】"]},{"code":401,"indent":0,"parameters":["啊！糟糕……"]},{"code":101,"indent":0,"parameters":["Ay",0,0,2]},{"code":401,"indent":0,"parameters":["【安雅】"]},{"code":401,"indent":0,"parameters":["我到底在做什么啊……"]},{"code":401,"indent":0,"parameters":["一开始就没意识到严重性么……"]},{"code":401,"indent":0,"parameters":["天了……"]},{"code":101,"indent":0,"parameters":["",0,0,2]},{"code":401,"indent":0,"parameters":["就这样……\\!辰远在与安雅互动的过程中……"]},{"code":401,"indent":0,"parameters":["一不小心玩脱了……\\!"]},{"code":401,"indent":0,"parameters":["就落下了这个结果……\\!"]},{"code":401,"indent":0,"parameters":["很无奈的为自己的生命画上了句号……"]},{"code":230,"indent":0,"parameters":[240]},{"code":353,"indent":0,"parameters":[]},{"code":0,"indent":0,"parameters":[]}],"moveFrequency":3,"moveRoute":{"list":[{"code":0,"parameters":[]}],"repeat":true,"skippable":false,"wait":false},"moveSpeed":3,"moveType":0,"priorityType":0,"stepAnime":false,"through":false,"trigger":4,"walkAnime":true},{"conditions":{"actorId":1,"actorValid":false,"itemId":1,"itemValid":false,"selfSwitchCh":"A","selfSwitchValid":false,"switch1Id":1,"switch1Valid":false,"switch2Id":1,"switch2Valid":false,"variableId":44,"variableValid":true,"variableValue":100},"directionFix":false,"image":{"characterIndex":0,"characterName":"","direction":2,"pattern":0,"tileId":0},"list":[{"code":111,"indent":0,"parameters":[4,1,0]},{"code":235,"indent":1,"parameters":[1]},{"code":235,"indent":1,"parameters":[2]},{"code":235,"indent":1,"parameters":[3]},{"code":124,"indent":1,"parameters":[1]},{"code":0,"indent":1,"parameters":[]},{"code":412,"indent":0,"parameters":[]},{"code":231,"indent":0,"parameters":[1,"7-19",0,0,0,0,100,100,255,0]},{"code":101,"indent":0,"parameters":["player",3,0,2]},{"code":401,"indent":0,"parameters":["【辰远】"]},{"code":401,"indent":0,"parameters":["啊……不要在这……结束啊……"]},{"code":250,"indent":0,"parameters":[{"name":"[taji","volume":90,"pitch":100,"pan":0}]},{"code":230,"indent":0,"parameters":[60]},{"code":250,"indent":0,"parameters":[{"name":"[Bite","volume":90,"pitch":100,"pan":0}]},{"code":222,"indent":0,"parameters":[]},{"code":230,"indent":0,"parameters":[180]},{"code":101,"indent":0,"parameters":["Ay",0,0,2]},{"code":401,"indent":0,"parameters":["【安雅】"]},{"code":401,"indent":0,"parameters":["！！！！！完了！"]},{"code":101,"indent":0,"parameters":["Ay",0,0,2]},{"code":401,"indent":0,"parameters":["【安雅】"]},{"code":401,"indent":0,"parameters":["小家伙……你还好么……"]},{"code":401,"indent":0,"parameters":["你……"]},{"code":101,"indent":0,"parameters":["Ay",0,0,2]},{"code":401,"indent":0,"parameters":["【安雅】"]},{"code":401,"indent":0,"parameters":["啊啊啊！！！"]},{"code":401,"indent":0,"parameters":["你可别死啊……怎么会这样！"]},{"code":401,"indent":0,"parameters":["……我到底在做什么啊……？"]},{"code":101,"indent":0,"parameters":["",0,0,2]},{"code":401,"indent":0,"parameters":["就这样……\\!辰远在与安雅互动的过程中……"]},{"code":401,"indent":0,"parameters":["一不小心玩脱了……\\!"]},{"code":401,"indent":0,"parameters":["就落下了这个结果……\\!"]},{"code":401,"indent":0,"parameters":["很无奈的为自己的生命画上了句号……"]},{"code":230,"indent":0,"parameters":[240]},{"code":353,"indent":0,"parameters":[]},{"code":0,"indent":0,"parameters":[]}],"moveFrequency":3,"moveRoute":{"list":[{"code":0,"parameters":[]}],"repeat":true,"skippable":false,"wait":false},"moveSpeed":3,"moveType":0,"priorityType":0,"stepAnime":false,"through":false,"trigger":4,"walkAnime":true}],"x":0,"y":0}
]
}